libstc_geck/__init__.py
libstc_geck/advices.py
libstc_geck/cli.py
libstc_geck/client.py
libstc_geck/exceptions.py
libstc_geck/utils.py
libstc_geck-2.1.7.dist-info/METADATA
libstc_geck-2.1.7.dist-info/WHEEL
libstc_geck-2.1.7.dist-info/entry_points.txt
libstc_geck-2.1.7.dist-info/RECORD
