Metadata-Version: 2.1
Name: libstc-geck
Version: 2.1.7
Summary: GECK (Garden Of Eden Creation Kit) is a toolkit for setting up and maintaning STC
Author: Multilingual Loiter
Classifier: Programming Language :: Python :: 2
Classifier: Programming Language :: Python :: 2.7
Classifier: Programming Language :: Python :: 3
Classifier: Programming Language :: Python :: 3.4
Classifier: Programming Language :: Python :: 3.5
Classifier: Programming Language :: Python :: 3.6
Classifier: Programming Language :: Python :: 3.7
Classifier: Programming Language :: Python :: 3.8
Classifier: Programming Language :: Python :: 3.9
Classifier: Programming Language :: Python :: 3.10
Classifier: Programming Language :: Python :: 3.11
Classifier: Programming Language :: Python :: 3.12
Requires-Dist: aiohttp (>=3.11,<3.12)
Requires-Dist: aiokit (>=1.3,<1.4)
Requires-Dist: aiosumma (>=2,<3)
Requires-Dist: fire (>=0.7,<0.8)
Requires-Dist: humanfriendly (>=10.0,<10.1)
Requires-Dist: ipfs-hamt-directory-py (>=0.1.1,<0.2.0)
Requires-Dist: izihawa-ipfs-api (>=1.0.7,<1.1.0)
Requires-Dist: izihawa-utils (>=1.2,<1.3)
Requires-Dist: multidict (>=6,<7)
Requires-Dist: summa-embed (>=0.25,<0.26)
Requires-Dist: termcolor (>=2,<3)
